taskcapsule/__init__.py
taskcapsule/taskcapsule.py
taskcapsule-0.2.1.dist-info/licenses/LICENSE
taskcapsule-0.2.1.dist-info/METADATA
taskcapsule-0.2.1.dist-info/WHEEL
taskcapsule-0.2.1.dist-info/top_level.txt
taskcapsule-0.2.1.dist-info/RECORD
