Metadata-Version: 2.4
Name: taskcapsule
Version: 0.2.1
Summary: A simple task runner for Python
Author-email: Scott Walsh <scott@invisiblethreat.ca>
License: MIT
Project-URL: repository, https://github.com/invisiblethreat/taskcapsule
Project-URL: homepage, https://github.com/invisiblethreat/taskcapsule
Project-URL: documentation, https://github.com/invisiblethreat/taskcapsule
Keywords: taskcapsule
Classifier: Programming Language :: Python :: 3
Classifier: Programming Language :: Python :: 3.12
Classifier: License :: OSI Approved :: MIT License
Classifier: Operating System :: OS Independent
Requires-Python: >=3.12
License-File: LICENSE
Requires-Dist: pydantic>=2.11.3
Dynamic: license-file
